_pyjq.cpython-39-darwin.so
pyjq.py
pyjq-2.5.2.dist-info/LICENSE
pyjq-2.5.2.dist-info/METADATA
pyjq-2.5.2.dist-info/WHEEL
pyjq-2.5.2.dist-info/top_level.txt
pyjq-2.5.2.dist-info/RECORD
