Metadata-Version: 2.1
Name: pyjq
Version: 2.5.2
Summary: Binding for jq JSON processor.
Home-page: http://github.com/doloopwhile/pyjq
Author: Omoto Kenji
License: MIT License
Keywords: jq
Platform: UNKNOWN
Classifier: Development Status :: 5 - Production/Stable
Classifier: Intended Audience :: Developers
Classifier: Natural Language :: English
Classifier: License :: OSI Approved :: MIT License
Classifier: Programming Language :: Python
Classifier: Programming Language :: Python :: 3
Classifier: Programming Language :: Python :: 3.7
Classifier: Programming Language :: Python :: 3.8
Classifier: Programming Language :: Python :: 3.9
Classifier: Programming Language :: JavaScript
